jrjModelRegistry/__init__.py
jrjModelRegistry/jrjModelRegistry.py
jrjModelRegistry/mongo.py
jrjModelRegistry/frontend/index.html
jrjModelRegistry/frontend/package.json
jrjModelRegistry/frontend/vite.config.js
jrjModelRegistry/frontend/dist/index.html
jrjModelRegistry/frontend/dist/assets/index-B6snAd4S.css
jrjModelRegistry/frontend/dist/assets/index-uC3TUECw.js
jrjModelRegistry/frontend/src/configUtils.js
jrjModelRegistry/frontend/src/utils/apis.js
jrjmodelregistry-1.0.14.dist-info/licenses/LICENSE
jrjmodelregistry-1.0.14.dist-info/METADATA
jrjmodelregistry-1.0.14.dist-info/WHEEL
jrjmodelregistry-1.0.14.dist-info/top_level.txt
jrjmodelregistry-1.0.14.dist-info/RECORD
